{
  "source": "get_design_context",
  "nodeId": "1:11",
  "fetchedAt": "2026-07-04T09:04:00+09:00",
  "page": "top",
  "section": "header-inner",
  "specs": {
    "innerMaxWidth": "1248px",
    "innerPadding": "4px 24px",
    "borderRadius": "12px",
    "boxShadow": "0 0 5px rgba(123,123,123,0.2)",
    "headerOuterPadding": "16px",
    "logoSize": "104 x 23.891px",
    "navLinkWidth": "104px",
    "navLinkPaddingY": "24px",
    "navFont": "Poppins SemiBold 16px / 22.4px / #1e1e1e",
    "contactWidth": "144px",
    "contactPadding": "16px 20px",
    "contactFont": "Poppins Bold 16px / white",
    "contactRadius": "48px",
    "contactBg": "#0096df"
  }
}
